CSV_Samples/MasterTemplate.csv
CSV_Samples/Pond5-sample.csv
CSV_Samples/Sample_Adobe_Stock_CSV_upload.csv
CSV_Samples/shutterstock_content_upload.csv
src/__init__.py
src/stock_contributor_csv_descriptors/__init__.py
src/stock_contributor_csv_descriptors/generate_csv_for_stock_websites.py
src/stock_contributor_csv_descriptors/populate_file_names_to_main_csv.py
venv/Lib/site-packages/_virtualenv.py
venv/Lib/site-packages/_distutils_hack/__init__.py
venv/Lib/site-packages/_distutils_hack/override.py
venv/Lib/site-packages/filetype/__init__.py
venv/Lib/site-packages/filetype/__main__.py
venv/Lib/site-packages/filetype/filetype.py
venv/Lib/site-packages/filetype/helpers.py
venv/Lib/site-packages/filetype/match.py
venv/Lib/site-packages/filetype/utils.py
venv/Lib/site-packages/filetype/types/__init__.py
venv/Lib/site-packages/filetype/types/application.py
venv/Lib/site-packages/filetype/types/archive.py
venv/Lib/site-packages/filetype/types/audio.py
venv/Lib/site-packages/filetype/types/base.py
venv/Lib/site-packages/filetype/types/document.py
venv/Lib/site-packages/filetype/types/font.py
venv/Lib/site-packages/filetype/types/image.py
venv/Lib/site-packages/filetype/types/isobmff.py
venv/Lib/site-packages/filetype/types/video.py
venv/Lib/site-packages/pip/__init__.py
venv/Lib/site-packages/pip/__main__.py
venv/Lib/site-packages/pip/_internal/__init__.py
venv/Lib/site-packages/pip/_internal/build_env.py
venv/Lib/site-packages/pip/_internal/cache.py
venv/Lib/site-packages/pip/_internal/configuration.py
venv/Lib/site-packages/pip/_internal/exceptions.py
venv/Lib/site-packages/pip/_internal/main.py
venv/Lib/site-packages/pip/_internal/pyproject.py
venv/Lib/site-packages/pip/_internal/self_outdated_check.py
venv/Lib/site-packages/pip/_internal/wheel_builder.py
venv/Lib/site-packages/pip/_internal/cli/__init__.py
venv/Lib/site-packages/pip/_internal/cli/autocompletion.py
venv/Lib/site-packages/pip/_internal/cli/base_command.py
stock_contributor_csv_descriptors-0.1.2.dist-info/LICENSE
stock_contributor_csv_descriptors-0.1.2.dist-info/METADATA
stock_contributor_csv_descriptors-0.1.2.dist-info/WHEEL
stock_contributor_csv_descriptors-0.1.2.dist-info/entry_points.txt
stock_contributor_csv_descriptors-0.1.2.dist-info/top_level.txt
stock_contributor_csv_descriptors-0.1.2.dist-info/RECORD
