Metadata-Version: 2.1
Name: stock-contributor-csv-descriptors
Version: 0.1.2
Summary: Output a CSV file for each selected stock website (such as Adobe Stock, Shutterstock, ...)
Author-email: Sylvain Riondet <sylvainriondet@gmail.com>
Project-URL: Homepage, https://github.com/sylvain-ri/stock-contributor-csv-descriptors
Classifier: Programming Language :: Python :: 3
Classifier: License :: OSI Approved :: GNU General Public License v3 (GPLv3)
Classifier: Operating System :: OS Independent
Requires-Python: >=3.7
License-File: LICENSE
Requires-Dist: filetype
